pyaduct/__init__.py
pyaduct/broker.py
pyaduct/certs.py
pyaduct/client.py
pyaduct/factory.py
pyaduct/main.py
pyaduct/models.py
pyaduct/store.py
pyaduct/utils.py
pyaduct-0.1.2.dist-info/METADATA
pyaduct-0.1.2.dist-info/WHEEL
pyaduct-0.1.2.dist-info/entry_points.txt
pyaduct-0.1.2.dist-info/licenses/LICENSE
pyaduct-0.1.2.dist-info/RECORD
